kpsh/__init__.py
kpsh/app.py
kpsh/autotype/__init__.py
kpsh/autotype/commands.py
kpsh/autotype/placeholders.py
kpsh/autotype/wtypekeys.py
kpsh/autotype/xdotoolkeys.py
kpsh/autotype/ydotoolkeys.py
kpsh/cleanup.py
kpsh/clipboard.py
kpsh/commands.py
kpsh/completion.py
kpsh/db.py
kpsh/entry.py
kpsh/environment.py
kpsh/io.py
kpsh/threads.py
kpsh-2.2.0.data/scripts/kpsh-client
kpsh-2.2.0.data/scripts/kpsh-detect-backend-sway
kpsh-2.2.0.data/scripts/kpsh-menu
kpsh-2.2.0.dist-info/LICENSE
kpsh-2.2.0.dist-info/METADATA
kpsh-2.2.0.dist-info/WHEEL
kpsh-2.2.0.dist-info/entry_points.txt
kpsh-2.2.0.dist-info/RECORD
