Metadata-Version: 2.1
Name: kpsh
Version: 2.2.0
Summary: KeePass shell interface and daemon
Home-page: https://git.goral.net.pl/mgoral/keepass-shell
License: GPL-3.0-or-later
Keywords: keepass,shell,password,cli,tui
Author: Michal Goral
Author-email: dev@goral.net.pl
Requires-Python: >=3.8,<4.0
Classifier: Development Status :: 5 - Production/Stable
Classifier: Environment :: Console
Classifier: Intended Audience :: End Users/Desktop
Classifier: License :: OSI Approved :: GNU General Public License v3 or later (GPLv3+)
Classifier: Natural Language :: English
Classifier: Operating System :: POSIX
Classifier: Programming Language :: Python :: 3
Classifier: Programming Language :: Python :: 3.8
Classifier: Programming Language :: Python :: 3.9
Classifier: Programming Language :: Python :: 3.10
Classifier: Programming Language :: Python :: 3.11
Classifier: Topic :: Utilities
Requires-Dist: importlib-metadata (>=1.0,<2.0) ; python_version >= "3.8" and python_version < "4.0"
Requires-Dist: prompt_toolkit (>=3.0.21,<4.0.0)
Requires-Dist: pykeepass (>=4.0.0,<5.0.0)
Project-URL: Documentation, https://git.goral.net.pl/mgoral/keepass-shell/src/branch/master/docs
Project-URL: Repository, https://git.goral.net.pl/mgoral/keepass-shell
